distinguishedname.py
distinguishedname-1.0.2.dist-info/WHEEL
distinguishedname-1.0.2.dist-info/METADATA
distinguishedname-1.0.2.dist-info/RECORD
