Metadata-Version: 2.1
Name: distinguishedname
Version: 1.0.2
Summary: I parse and create RFC2253 compliant distinguished names (DNs)
Keywords: distinguishedname,dn,rdn,rfc2253,pki
Author-email: Mark Wright <markscottwright@gmail.com>
Requires-Python: >=3.8
Classifier: Programming Language :: Python :: 3
Classifier: License :: OSI Approved :: MIT License
Classifier: Operating System :: OS Independent
Project-URL: Homepage, https://github.com/markscottwright/distinguishedname
Project-URL: Issues, https://github.com/markscottwright/distinguishedname/issues
